common_atd_eag/__init__.py
common_atd_eag/core.py
common_atd_eag-0.0.2.dist-info/LICENSE
common_atd_eag-0.0.2.dist-info/METADATA
common_atd_eag-0.0.2.dist-info/WHEEL
common_atd_eag-0.0.2.dist-info/top_level.txt
common_atd_eag-0.0.2.dist-info/RECORD
