Metadata-Version: 2.1
Name: common-atd-eag
Version: 0.0.2
Summary: Common package for atd-eag
Author-email: anonymous <anonymous@email.com>
License: MIT
Project-URL: homepage, https://github.com/anonymous/common_atd_eag
Requires-Python: >=3.7
License-File: LICENSE
